[
  {
    "id": 1,
    "titulo": "Carne Assada",
    "imagem": "recipes/recipe-1.jpeg",
    "tempo_preparo": "15min",
    "tempo_cozimento": "5min",
    "tags": ["Carne", "Almoço"],
    "ingredientes": ["1kg de carne", "Sal", "Pimenta", "Alecrim"],
    "modo_preparo": ["Tempere a carne com sal e pimenta.", "Deixe marinar por 2 horas.", "Asse em fogo médio por 15 minutos."]
  },
  {
    "id": 2,
    "titulo": "Costela",
    "imagem": "recipes/recipe-2.jpeg",
    "tempo_preparo": "30min",
    "tempo_cozimento": "40min",
    "tags": ["Carne", "Jantar"],
    "ingredientes": ["2kg de costela", "Molho Barbecue", "Sal grosso"],
    "modo_preparo": ["Ferva a costela na água com sal.", "Escorra e passe o molho barbecue.", "Leve ao forno por 40 minutos."]
  },
  {
    "id": 3,
    "titulo": "Sopa de Vegetais",
    "imagem": "recipes/recipe-3.jpeg",
    "tempo_preparo": "10min",
    "tempo_cozimento": "20min",
    "tags": ["Vegetariano", "Sopa"],
    "ingredientes": ["3 Cenouras", "4 Batatas", "1 Litro de Água", "Salsinha"],
    "modo_preparo": ["Corte todos os legumes em cubos.", "Cozinhe na água fervente até ficarem macios.", "Tempere a gosto."]
  },
  {
    "id": 4,
    "titulo": "Panqueca de Banana",
    "imagem": "recipes/recipe-4.jpeg",
    "tempo_preparo": "5min",
    "tempo_cozimento": "5min",
    "tags": ["Café da manhã", "Doce"],
    "ingredientes": ["2 Bananas maduras", "2 Ovos", "1 xícara de Aveia", "Canela"],
    "modo_preparo": ["Amasse as bananas.", "Misture com os ovos e a aveia.", "Frite em uma frigideira untada até dourar."]
  }
]